Workbook

Sheet Executive Summary
A1: MULTIFAMILY ACQUISITION ANALYSIS
A3: PROPERTY OVERVIEW
A4: Property Name: | B4: 518 East 83rd Street
A5: Address: | B5: New York, NY 10028
A6: Total Units: | B6: =Inputs!B8 -> 20
A7: Gross Floor Area (SF): | B7: =Inputs!B9 -> 8120
A8: Price per Unit: | B8: =Inputs!B13/Inputs!B8 -> 410000
A9: Price per SF: | B9: =Inputs!B13/Inputs!B9 -> 1009.8522
A11: KEY METRICS
A12: In-Place Cap Rate: | B12: =Inputs!B25/Inputs!B13 -> 0.04076219
A13: Proforma Cap Rate: | B13: =Inputs!B26/Inputs!B13 -> 0.05731439
A14: Year 1 NOI: | B14: =ProForma!C20 -> 311233.61
A15: Year 1 Cash-on-Cash: | B15: =ProForma!C24/ProForma!B30 -> -1.5928108

Sheet Inputs
A1: ACQUISITION INPUTS
A3: PROPERTY INFORMATION
A4: Property Name: | B4: 518 East 83rd Street
A5: Address: | B5: New York, NY 10028
A6: Year Built: | B6: 1910
A7: Building Class: | B7: C1
A8: Total Units: | B8: 20
A9: Gross Floor Area (SF): | B9: 8120
A11: ACQUISITION DETAILS
A12: Offering Price: | B12: Asking Price
A13: Purchase Price: | B13: 8200000
A14: Closing Costs (%): | B14: 0.025
A15: Closing Costs ($): | B15: =B13*B14 -> 205000
A16: Immediate CapEx: | B16: 0
A17: Total Acquisition Cost: | B17: =B13+B15+B16 -> 8405000
A19: CURRENT FINANCIALS
A20: In-Place Gross Rent: | B20: 551152
A21: Vacancy Loss (%): | B21: 0.02
A22: Other Income: | B22: 8351
A23: Effective Gross Income: | B23: =B20*(1-B21)+B22 -> 548479.96
A24: Operating Expenses: | B24: 214230
A25: In-Place NOI: | B25: =B23-B24 -> 334249.96
A26: Proforma NOI: | B26: 469978
A28: OPERATING ASSUMPTIONS
A29: Annual Rent Growth: | B29: 0.03
A30: Annual Expense Growth: | B30: 0.025
A31: Stabilized Vacancy (%): | B31: 0.05
A32: CapEx Reserve (per unit): | B32: 500
A34: FINANCING TERMS
A35: Loan-to-Value (%): | B35: 0.65
A36: Loan Amount: | B36: =B13*B35 -> 5330000
A37: Interest Rate: | B37: 0.065
A38: Amortization (Years): | B38: 30
A39: Annual Debt Service: | B39: =PMT(B37,B38,B36)*-12 -> 4897893.2
A41: EXIT ASSUMPTIONS
A42: Hold Period (Years): | B42: 5
A43: Exit Cap Rate: | B43: 0.055
A44: Selling Costs (%): | B44: 0.06

Sheet ProForma
A1: 10-YEAR PRO FORMA
B3: Acq | C3: Year 1 | D3: Year 2 | E3: Year 3 | F3: Year 4 | G3: Year 5
A5: REVENUE
A6: Gross Rental Income | B6: =Inputs!B20 -> 551152 | C6: =B6*(1+Inputs!$B$29) -> 567686.56 | D6: =C6*(1+Inputs!$B$29) -> 584717.16 | E6: =D6*(1+Inputs!$B$29) -> 602258.67 | F6: =E6*(1+Inputs!$B$29) -> 620326.43 | G6: =F6*(1+Inputs!$B$29) -> 638936.22
A7: Vacancy Loss | B7: =-B6*Inputs!$B$31 -> -27557.6 | C7: =-C6*Inputs!$B$31 -> -28384.328 | D7: =-D6*Inputs!$B$31 -> -29235.858 | E7: =-E6*Inputs!$B$31 -> -30112.934 | F7: =-F6*Inputs!$B$31 -> -31016.322 | G7: =-G6*Inputs!$B$31 -> -31946.811
A8: Other Income | B8: =Inputs!B22 -> 8351 | C8: =B8*(1+Inputs!$B$29) -> 8601.53 | D8: =C8*(1+Inputs!$B$29) -> 8859.5759 | E8: =D8*(1+Inputs!$B$29) -> 9125.3632 | F8: =E8*(1+Inputs!$B$29) -> 9399.1241 | G8: =F8*(1+Inputs!$B$29) -> 9681.0978
A9: Effective Gross Income | B9: =SUM(B6:B8) -> 531945.4 | C9: =SUM(C6:C8) -> 547903.76 | D9: =SUM(D6:D8) -> 564340.87 | E9: =SUM(E6:E8) -> 581271.1 | F9: =SUM(F6:F8) -> 598709.23 | G9: =SUM(G6:G8) -> 616670.51
A11: OPERATING EXPENSES
A12: Property Taxes | B12: 128935 | C12: =B12*(1+Inputs!$B$30) -> 132158.38 | D12: =C12*(1+Inputs!$B$30) -> 135462.33 | E12: =D12*(1+Inputs!$B$30) -> 138848.89 | F12: =E12*(1+Inputs!$B$30) -> 142320.12 | G12: =F12*(1+Inputs!$B$30) -> 145878.12
A13: Insurance | B13: 12065 | C13: =B13*(1+Inputs!$B$30) -> 12366.625 | D13: =C13*(1+Inputs!$B$30) -> 12675.791 | E13: =D13*(1+Inputs!$B$30) -> 12992.685 | F13: =E13*(1+Inputs!$B$30) -> 13317.503 | G13: =F13*(1+Inputs!$B$30) -> 13650.44
A14: Utilities | B14: 36900 | C14: =B14*(1+Inputs!$B$30) -> 37822.5 | D14: =C14*(1+Inputs!$B$30) -> 38768.062 | E14: =D14*(1+Inputs!$B$30) -> 39737.264 | F14: =E14*(1+Inputs!$B$30) -> 40730.696 | G14: =F14*(1+Inputs!$B$30) -> 41748.963
A15: Repairs & Maintenance | B15: 21860 | C15: =B15*(1+Inputs!$B$30) -> 22406.5 | D15: =C15*(1+Inputs!$B$30) -> 22966.662 | E15: =D15*(1+Inputs!$B$30) -> 23540.829 | F15: =E15*(1+Inputs!$B$30) -> 24129.35 | G15: =F15*(1+Inputs!$B$30) -> 24732.584
A16: Management Fee (4% of EGI) | B16: =B9*0.04 -> 21277.816 | C16: =C9*0.04 -> 21916.15 | D16: =D9*0.04 -> 22573.635 | E16: =E9*0.04 -> 23250.844 | F16: =F9*0.04 -> 23948.369 | G16: =G9*0.04 -> 24666.82
A17: CapEx Reserve | B17: =Inputs!$B$8*Inputs!$B$32 -> 10000 | C17: =Inputs!$B$8*Inputs!$B$32 -> 10000 | D17: =Inputs!$B$8*Inputs!$B$32 -> 10000 | E17: =Inputs!$B$8*Inputs!$B$32 -> 10000 | F17: =Inputs!$B$8*Inputs!$B$32 -> 10000 | G17: =Inputs!$B$8*Inputs!$B$32 -> 10000
A18: Total Operating Expenses | B18: =SUM(B12:B17) -> 231037.82 | C18: =SUM(C12:C17) -> 236670.15 | D18: =SUM(D12:D17) -> 242446.48 | E18: =SUM(E12:E17) -> 248370.52 | F18: =SUM(F12:F17) -> 254446.03 | G18: =SUM(G12:G17) -> 260676.93
A20: NET OPERATING INCOME | B20: =B9-B18 -> 300907.58 | C20: =C9-C18 -> 311233.61 | D20: =D9-D18 -> 321894.39 | E20: =E9-E18 -> 332900.59 | F20: =F9-F18 -> 344263.2 | G20: =G9-G18 -> 355993.59
A22: CASH FLOW
A23: Less: Debt Service | B23: =-Inputs!$B$39 -> -4897893.2 | C23: =-Inputs!$B$39 -> -4897893.2 | D23: =-Inputs!$B$39 -> -4897893.2 | E23: =-Inputs!$B$39 -> -4897893.2 | F23: =-Inputs!$B$39 -> -4897893.2 | G23: =-Inputs!$B$39 -> -4897893.2
A24: Cash Flow Before Tax | B24: =B21+B23 -> -4897893.2 | C24: =C21+C23 -> -4897893.2 | D24: =D21+D23 -> -4897893.2 | E24: =E21+E23 -> -4897893.2 | F24: =F21+F23 -> -4897893.2 | G24: =G21+G23 -> -4897893.2
A27: INVESTMENT SUMMARY
A28: Total Acquisition Cost | B28: =Inputs!B17 -> 8405000
A29: Less: Loan Proceeds | B29: =-Inputs!B36 -> -5330000
A30: Equity Required | B30: =B28+B29 -> 3075000

Sheet Unit Mix
A1: UNIT MIX ANALYSIS
A3: Unit | B3: Status | C3: Beds/Baths | D3: SF | E3: Current Rent | F3: Market Rent | G3: Upside
A4: 1A | B4: FM | C4: 1/1 | D4: 320 | E4: 2480 | F4: 2675 | G4: =F4-E4 -> 195
A5: 1B | B5: FM | C5: 1/1 | D5: 325 | E5: 2550 | F5: 2805 | G5: =F5-E5 -> 255
A6: 1C | B6: Vacant | C6: 2/2 | D6: 900 | E6: 0 | F6: 5500 | G6: =F6-E6 -> 5500
A7: 1D | B7: RS | C7: 1/1 | D7: 425 | E7: 834 | F7: 834 | G7: =F7-E7 -> 0
A8: 2A | B8: FM | C8: 1/1 | D8: 425 | E8: 2595 | F8: 2810 | G8: =F8-E8 -> 215
A9: 2B | B9: FM | C9: 1/1 | D9: 425 | E9: 2800 | F9: 2830 | G9: =F9-E9 -> 30
A10: 2C | B10: FM | C10: 1/1 | D10: 400 | E10: 2700 | F10: 2820 | G10: =F10-E10 -> 120
A11: 2D | B11: FM | C11: 1/1 | D11: 400 | E11: 2500 | F11: 2800 | G11: =F11-E11 -> 300
A12: 3A | B12: Vacant | C12: 1/1 | D12: 425 | E12: 0 | F12: 3400 | G12: =F12-E12 -> 3400
A13: 3B | B13: FM | C13: 1/1 | D13: 425 | E13: 3000 | F13: 2850 | G13: =F13-E13 -> -150
A14: 3C | B14: FM | C14: S/1 | D14: 400 | E14: 2600 | F14: 2810 | G14: =F14-E14 -> 210
A15: 3D | B15: FM | C15: 1/1 | D15: 400 | E15: 2595 | F15: 2810 | G15: =F15-E15 -> 215
... A23: 5D | B23: FM | C23: 1/1 | D23: 405 | E23: 2700 | F23: 2820 | G23: =F23-E23 -> 120
A24: TOTAL | D24: =SUM(D4:D23) -> 8575 | E24: =SUM(E4:E23) -> 45929 | F24: =SUM(F4:F23) -> 57472 | G24: =SUM(G4:G23) -> 11543
A26: RENT ANALYSIS
A27: Avg Rent per Unit (In-Place): | B27: =E24/20 -> 2296.45
A28: Avg Rent per Unit (Market): | B28: =F24/20 -> 2873.6
A29: Avg Rent per SF (In-Place): | B29: =E24/D24 -> 5.3561516
A30: Avg Rent per SF (Market): | B30: =F24/D24 -> 6.7022741
A32: Annual Mark-to-Market Upside: | B32: =G24*12 -> 138516
A33: Upside (%): | B33: =(F24-E24)/E24 -> 0.25132269

Sheet Sensitivity
A1: SENSITIVITY ANALYSIS
A3: LEVERED IRR SENSITIVITY
A4: Exit Cap Rate Scenarios
A5: Scenario | B5: Exit Cap | C5: Exit NOI | D5: Exit Value | E5: Proceeds | F5: Levered IRR
A6: Base Case (5.5%) | B6: 0.055 | C6: =ProForma!G20 -> 355993.59 | D6: =C6/B6 -> 6472610.7 | E6: =D6*(1-Inputs!$B$44) -> 6084254
A7: Optimistic (5.0%) | B7: 0.05 | C7: =ProForma!G20 -> 355993.59 | D7: =C7/B7 -> 7119871.7 | E7: =D7*(1-Inputs!$B$44) -> 6692679.4
A8: Pessimistic (6.0%) | B8: 0.06 | C8: =ProForma!G20 -> 355993.59 | D8: =C8/B8 -> 5933226.4 | E8: =D8*(1-Inputs!$B$44) -> 5577232.8
A9: Conservative (6.5%) | B9: 0.065 | C9: =ProForma!G20 -> 355993.59 | D9: =C9/B9 -> 5476824.4 | E9: =D9*(1-Inputs!$B$44) -> 5148214.9
A12: PURCHASE PRICE SENSITIVITY
A13: Purchase Price Scenarios
A14: Scenario | B14: Price | C14: Entry Cap | D14: Price/Unit | E14: Price/SF
A15: Asking Price | B15: 8200000 | C15: =Inputs!$B$25/B15 -> 0.04076219 | D15: =B15/Inputs!$B$8 -> 410000 | E15: =B15/Inputs!$B$9 -> 1009.8522
A16: 5% Discount | B16: 7790000 | C16: =Inputs!$B$25/B16 -> 0.042907569 | D16: =B16/Inputs!$B$8 -> 389500 | E16: =B16/Inputs!$B$9 -> 959.35961
A17: 10% Discount | B17: 7380000 | C17: =Inputs!$B$25/B17 -> 0.045291322 | D17: =B17/Inputs!$B$8 -> 369000 | E17: =B17/Inputs!$B$9 -> 908.867
A18: List Price | B18: 8200000 | C18: =Inputs!$B$25/B18 -> 0.04076219 | D18: =B18/Inputs!$B$8 -> 410000 | E18: =B18/Inputs!$B$9 -> 1009.8522
A21: KEY INVESTMENT METRICS
A22: Metric | B22: Value
A23: Year 1 Cash-on-Cash | B23: =ProForma!C24/ProForma!B30 -> -1.5928108
A24: Year 1 DSCR | B24: =ProForma!C20/Inputs!B39 -> 0.063544385
A25: Stabilized Cap Rate | B25: =Inputs!B26/Inputs!B13 -> 0.05731439
A26: Price per Unit | B26: =Inputs!B13/Inputs!B8 -> 410000
A27: Price per SF | B27: =Inputs!B13/Inputs!B9 -> 1009.8522
