Workbook

Sheet Executive Summary
A1: VALUE-ADD RENOVATION BUDGET
A2: Comprehensive Cost Planning & ROI Analysis
A4: PROPERTY OVERVIEW
A5: Property Name: | B5: =Inputs!B2
A6: Address: | B6: =Inputs!B3
A7: Total Units: | B7: =Inputs!B4
A8: Building Class: | B8: =Inputs!B5
A9: Average Unit Size (SF): | B9: =Inputs!B6
A11: TOTAL RENOVATION BUDGET
A12: Total Renovation Cost: | B12: ='Unit-Level Budget'!C100
A13: Cost per Unit: | B13: ='Unit-Level Budget'!C101
A14: Cost per SF: | B14: ='Unit-Level Budget'!C102
A15: Contingency Reserve (10%): | B15: ='Unit-Level Budget'!C103
A16: All-In Budget: | B16: ='Unit-Level Budget'!C104
A18: BUDGET BREAKDOWN BY CATEGORY
A19: Category | B19: Total Cost | C19: % of Total | D19: Cost/Unit
A20: Kitchen Renovations | B20: ='Unit-Level Budget'!C10 | C20: ='Unit-Level Budget'!D10 | D20: ='Unit-Level Budget'!E10
A21: Bathroom Renovations | B21: ='Unit-Level Budget'!C20 | C21: ='Unit-Level Budget'!D20 | D21: ='Unit-Level Budget'!E20
A22: Flooring | B22: ='Unit-Level Budget'!C30 | C22: ='Unit-Level Budget'!D30 | D22: ='Unit-Level Budget'!E30
A23: Paint & Finishes | B23: ='Unit-Level Budget'!C40 | C23: ='Unit-Level Budget'!D40 | D23: ='Unit-Level Budget'!E40
A24: Appliances & Fixtures | B24: ='Unit-Level Budget'!C50 | C24: ='Unit-Level Budget'!D50 | D24: ='Unit-Level Budget'!E50
A25: Exterior Improvements | B25: ='Unit-Level Budget'!C60 | C25: ='Unit-Level Budget'!D60 | D25: ='Unit-Level Budget'!E60
A26: Common Areas | B26: ='Unit-Level Budget'!C70 | C26: ='Unit-Level Budget'!D70 | D26: ='Unit-Level Budget'!E70
A29: VALUE CREATION & ROI
A31: Current Avg Monthly Rent: | B31: =Inputs!B10
A32: Pro Forma Monthly Rent: | B32: =Inputs!B11
A33: Monthly Rent Increase: | B33: =B31-B30
A34: Annual Rent Increase (per unit): | B34: =B32*12
A35: Total Annual Revenue Increase: | B35: =B33*Inputs!B4
A37: NOI Increase (60% margin): | B37: =B34*0.6
A38: Exit Cap Rate: | B38: =Inputs!B15
A39: Property Value Creation: | B39: =B36/B37
A41: Total Renovation Investment: | B41: =B15
A42: Value Creation/Investment (ROI): | B42: =B38/B40
A43: Payback Period (years): | B43: =B40/B36

Sheet Inputs
A1: PROPERTY & RENOVATION INPUTS
A2: All BLUE cells are inputs you can modify
A4: PROPERTY INFORMATION
A5: Property Name: | B5: Maple Gardens Apartments | C5: Enter property name
A6: Address: | B6: 123 Main Street
A7: Total Units: | B7: 50 | C7: Number of apartment units
A8: Building Class: | B8: Class B | C8: Class A, B, or C
A9: Average Unit Size (SF): | B9: 850
A11: CURRENT & PRO FORMA RENTS
A12: Current Avg Monthly Rent: | B12: 1800 | C12: Current in-place rent per unit
A13: Pro Forma Monthly Rent (Post-Reno): | B13: 2150 | C13: Expected rent after renovations
A14: Monthly Rent Increase: | B14: =B11-B10 | C14: Calculated automatically
A16: VALUE CREATION ASSUMPTIONS
A17: Exit Cap Rate: | B17: 0.055 | C17: Conservative cap rate for exit valuation
A18: NOI Margin: | B18: 0.6 | C18: 60% is typical for multifamily (40% OpEx)
A20: RENOVATION TIMELINE & PHASING
A21: Total Project Duration (months): | B21: 18 | C21: Total time for full property renovation
A22: Units per Phase: | B22: 10 | C22: Units renovated per phase
A23: Days per Unit Renovation: | B23: 21 | C23: Typical 3 weeks per unit
A24: Lost Rent per Unit during Reno (days): | B24: 30 | C24: Vacancy days per unit
A26: HOLDING COSTS DURING RENOVATION
A27: Monthly Debt Service (if applicable): | B27: 25000 | C27: Mortgage payment during renovation
A28: Monthly Operating Expenses (reduced): | B28: 15000 | C28: Utilities, insurance, etc.
A29: Monthly Management Fee (on occupied units): | B29: 3000 | C29: Property management

Sheet Cost Database
A1: RENOVATION COST DATABASE
A2: Pre-built cost ranges by building class - Use as reference for your estimates
A4: Item | B4: Class A | C4: Class B | D4: Class C | E4: Unit | F4: Notes
A5: KITCHEN RENOVATIONS
A6: Cabinet Refacing (paint) | B6: 3000 | C6: 2500 | D6: 2000 | E6: per kitchen | F6: Paint existing cabinets
A7: Cabinet Replacement - Stock | B7: 6500 | C7: 5000 | D7: 4000 | E7: per kitchen | F7: Stock cabinets from Home Depot/Lowes
A8: Cabinet Replacement - Semi-Custom | B8: 10000 | C8: 7500 | D8: 5500 | E8: per kitchen | F8: Better quality, more options
A9: Countertops - Laminate | B9: 1500 | C9: 1200 | D9: 1000 | E9: per kitchen | F9: Budget option
A10: Countertops - Granite | B10: 3000 | C10: 2500 | D10: 2000 | E10: per kitchen | F10: Mid-grade granite
A11: Countertops - Quartz | B11: 4000 | C11: 3200 | D11: 2500 | E11: per kitchen | F11: Premium option
A12: Appliance Package - Basic | B12: 2000 | C12: 1800 | D12: 1500 | E12: per kitchen | F12: White, basic features
A13: Appliance Package - Stainless | B13: 3500 | C13: 2800 | D13: 2200 | E13: per kitchen | F13: Stainless steel mid-grade
A14: Appliance Package - Premium | B14: 5000 | C14: 4000 | D14: 3000 | E14: per kitchen | F14: High-end brands
A15: Sink & Faucet | B15: 800 | C15: 600 | D15: 450 | E15: per kitchen | F15: Undermount sink + modern faucet
A16: Backsplash - Ceramic Tile | B16: 1200 | C16: 1000 | D16: 800 | E16: per kitchen | F16: Standard ceramic
A17: Backsplash - Subway Tile | B17: 1500 | C17: 1200 | D17: 900 | E17: per kitchen | F17: Popular white subway
... A20: Lighting - Pendant/Ceiling | B20: 500 | C20: 400 | D20: 300 | E20: per kitchen | F20: Modern fixtures
A22: BATHROOM RENOVATIONS
A23: Vanity - Stock (36") | B23: 800 | C23: 600 | D23: 450 | E23: per bath | F23: Basic vanity with sink
A24: Vanity - Semi-Custom (36") | B24: 1500 | C24: 1200 | D24: 900 | E24: per bath | F24: Better quality, more styles
A25: Vanity - Custom (36") | B25: 2500 | C25: 2000 | D25: 1500 | E25: per bath | F25: Premium custom vanity
A26: Toilet - Standard | B26: 250 | C26: 200 | D26: 150 | E26: per bath | F26: Basic commode
A27: Toilet - Comfort Height | B27: 400 | C27: 350 | D27: 280 | E27: per bath | F27: ADA height
A28: Toilet - Dual Flush | B28: 500 | C28: 400 | D28: 320 | E28: per bath | F28: Water-saving dual flush
A29: Tub Refinishing | B29: 500 | C29: 450 | D29: 380 | E29: per bath | F29: Reglaze existing tub
A30: Tub Replacement - Acrylic | B30: 1200 | C30: 1000 | D30: 800 | E30: per bath | F30: Standard 60" acrylic tub
A31: Tub Replacement - Cast Iron | B31: 2000 | C31: 1600 | D31: 1200 | E31: per bath | F31: Premium cast iron
A32: Shower - Fiberglass Insert | B32: 1500 | C32: 1200 | D32: 950 | E32: per shower | F32: Basic shower surround
A33: Shower - Tile Surround | B33: 3000 | C33: 2400 | D33: 1800 | E33: per shower | F33: Ceramic tile shower
A34: Shower - Premium Tile | B34: 4500 | C34: 3500 | D34: 2600 | E34: per shower | F34: Large format/designer tile
... A41: Mirror - Framed | B41: 300 | C41: 250 | D41: 200 | E41: per bath | F41: Decorative framed mirror
A43: FLOORING
A44: Carpet - Rental Grade | B44: 3 | C44: 2.5 | D44: 2 | E44: per SF | F44: Basic apartment carpet + pad
A45: Carpet - Mid-Grade | B45: 5 | C45: 4 | D45: 3.5 | E45: per SF | F45: Better quality, 7-10 year life
A46: Carpet - Premium | B46: 7 | C46: 6 | D46: 5 | E46: per SF | F46: Stain-resistant, 10-15 year life
A47: Vinyl Plank (LVP) - Builder | B47: 4 | C47: 3.5 | D47: 3 | E47: per SF | F47: Basic LVP, thin wear layer
A48: Vinyl Plank (LVP) - Mid-Grade | B48: 6 | C48: 5 | D48: 4.5 | E48: per SF | F48: 20mil wear layer, waterproof
A49: Vinyl Plank (LVP) - Premium | B49: 9 | C49: 7 | D49: 6 | E49: per SF | F49: Thick planks, enhanced visuals
A50: Laminate - Basic | B50: 3.5 | C50: 3 | D50: 2.5 | E50: per SF | F50: Entry-level laminate
A51: Laminate - Premium | B51: 6 | C51: 5 | D51: 4 | E51: per SF | F51: Better warranty, water-resistant
A52: Hardwood - Pre-Finished | B52: 12 | C52: 10 | D52: 8 | E52: per SF | F52: Solid hardwood, factory finish
A53: Hardwood - Engineered | B53: 9 | C53: 7.5 | D53: 6 | E53: per SF | F53: Engineered planks, more stable
A54: Tile - Ceramic | B54: 8 | C54: 6.5 | D54: 5.5 | E54: per SF | F54: Standard ceramic tile
A55: Tile - Porcelain | B55: 12 | C55: 10 | D55: 8 | E55: per SF | F55: Durable porcelain
A56: Tile - Large Format | B56: 15 | C56: 12 | D56: 10 | E56: per SF | F56: 12x24" or larger tiles
A58: PAINT & FINISHES
A59: Interior Paint - 1BR (SF) | B59: 2.5 | C59: 2 | D59: 1.75 | E59: per SF | F59: Walls + ceiling, 2 coats
A60: Interior Paint - 2BR (SF) | B60: 2.5 | C60: 2 | D60: 1.75 | E60: per SF | F60: Walls + ceiling, 2 coats
A61: Interior Paint - 3BR (SF) | B61: 2.5 | C61: 2 | D61: 1.75 | E61: per SF | F61: Walls + ceiling, 2 coats
A62: Accent Wall - Feature Color | B62: 200 | C62: 150 | D62: 120 | E62: per wall | F62: Single accent wall
A63: Trim & Baseboards - Paint | B63: 1.5 | C63: 1.2 | D63: 1 | E63: per LF | F63: Paint existing trim
A64: Trim & Baseboards - Replace | B64: 4 | C64: 3.5 | D64: 3 | E64: per LF | F64: New trim + paint
A65: Doors - Paint Existing | B65: 150 | C65: 120 | D65: 100 | E65: per door | F65: Paint existing doors
A66: Doors - Replace Interior | B66: 350 | C66: 280 | D66: 220 | E66: per door | F66: New door + hardware + paint
A67: Door Hardware - Upgrade | B67: 50 | C67: 40 | D67: 30 | E67: per door | F67: New handles/locks
A69: APPLIANCES & FIXTURES
A70: Light Fixtures - Basic | B70: 50 | C70: 40 | D70: 30 | E70: per fixture | F70: Builder-grade fixtures
A71: Light Fixtures - Mid-Grade | B71: 100 | C71: 80 | D71: 60 | E71: per fixture | F71: Brushed nickel, modern
A72: Light Fixtures - Premium | B72: 200 | C72: 150 | D72: 120 | E72: per fixture | F72: Designer fixtures
A73: Ceiling Fans | B73: 200 | C73: 150 | D73: 120 | E73: per fan | F73: With light kit
A74: Window Blinds - Vinyl | B74: 40 | C74: 35 | D74: 30 | E74: per window | F74: Basic vinyl blinds
A75: Window Blinds - Faux Wood | B75: 80 | C75: 65 | D75: 50 | E75: per window | F75: Better quality faux wood
A76: Thermostat - Programmable | B76: 150 | C76: 120 | D76: 100 | E76: per unit | F76: Digital programmable
A77: Thermostat - Smart (Nest/Ecobee) | B77: 250 | C77: 200 | D77: 160 | E77: per unit | F77: WiFi smart thermostat
A78: Smoke/CO Detectors - Hardwired | B78: 80 | C78: 65 | D78: 50 | E78: per unit | F78: Meet code requirements
A79: Washer/Dryer Hookups | B79: 300 | C79: 250 | D79: 200 | E79: per unit | F79: Install hookups if not existing
A80: Dishwasher - Basic | B80: 400 | C80: 350 | D80: 300 | E80: per unit | F80: Basic dishwasher
A81: Dishwasher - Stainless | B81: 600 | C81: 500 | D81: 400 | E81: per unit | F81: Stainless front
... A83: Microwave - Built-in | B83: 500 | C83: 400 | D83: 320 | E83: per unit | F83: Built-in microwave
A85: EXTERIOR IMPROVEMENTS
A86: Exterior Paint (SF) | B86: 3 | C86: 2.5 | D86: 2 | E86: per SF | F86: Building exterior painting
A87: Siding Repair (SF) | B87: 8 | C87: 6.5 | D87: 5 | E87: per SF | F87: Replace damaged siding
A88: Entry Door - Upgrade | B88: 800 | C88: 650 | D88: 500 | E88: per door | F88: New entry door + hardware
A89: Patio/Balcony - Resurface | B89: 1500 | C89: 1200 | D89: 900 | E89: per unit | F89: Resurface balcony
A90: Landscaping - Basic | B90: 3 | C90: 2.5 | D90: 2 | E90: per SF | F90: Basic landscaping per SF of grounds
A91: Landscaping - Enhanced | B91: 6 | C91: 5 | D91: 4 | E91: per SF | F91: Enhanced curb appeal package
A92: Tree Planting - Small | B92: 250 | C92: 200 | D92: 150 | E92: per tree | F92: 6-8ft tree
A93: Tree Planting - Large | B93: 800 | C93: 650 | D93: 500 | E93: per tree | F93: 12-15ft specimen tree
A94: Irrigation System (SF) | B94: 2.5 | C94: 2 | D94: 1.5 | E94: per SF | F94: Drip or spray irrigation
A95: Fencing - Chain Link | B95: 15 | C95: 12 | D95: 10 | E95: per LF | F95: Chain link fence
A96: Fencing - Wood Privacy | B96: 30 | C96: 25 | D96: 20 | E96: per LF | F96: Wood privacy fence
A97: Fencing - Vinyl | B97: 35 | C97: 28 | D97: 22 | E97: per LF | F97: Vinyl privacy fence
... A101: Signage - Monument Sign | B101: 8000 | C101: 6000 | D101: 4500 | E101: per property | F101: Monument/monument sign
A103: COMMON AREA IMPROVEMENTS
A104: Lobby Renovation (SF) | B104: 50 | C104: 40 | D104: 30 | E104: per SF | F104: Full lobby remodel
A105: Fitness Center Build-Out (SF) | B105: 40 | C105: 32 | D105: 25 | E105: per SF | F105: Create fitness center
A106: Pool Renovation - Replaster | B106: 8000 | C106: 6500 | D106: 5000 | E106: per pool | F106: Replaster existing pool
A107: Pool Renovation - Full | B107: 25000 | C107: 20000 | D107: 15000 | E107: per pool | F107: Complete pool renovation
A108: Pool Deck - Resurface | B108: 10 | C108: 8 | D108: 6 | E108: per SF | F108: Resurface pool deck
A109: Clubhouse Renovation (SF) | B109: 60 | C109: 48 | D109: 38 | E109: per SF | F109: Full clubhouse remodel
A110: Package Lockers - Amazon Hub | B110: 12000 | C110: 10000 | D110: 8000 | E110: per property | F110: 30-50 lockers
A111: Security System - Cameras | B111: 1500 | C111: 1200 | D111: 1000 | E111: per camera | F111: IP camera + install
A112: Security System - Access Control | B112: 500 | C112: 400 | D112: 320 | E112: per door | F112: Key fob access
A113: Mailbox Replacement | B113: 150 | C113: 120 | D113: 100 | E113: per unit | F113: USPS approved mailboxes
A114: Dog Park Build-Out | B114: 15000 | C114: 12000 | D114: 9000 | E114: per property | F114: Fenced dog park area
A115: Playground Equipment | B115: 20000 | C115: 15000 | D115: 12000 | E115: per property | F115: Commercial playground

Sheet Unit-Level Budget
A1: UNIT-BY-UNIT RENOVATION BUDGET
A2: Customize renovation scope and cost for each unit
A4: INSTRUCTIONS: Enter renovation costs for each unit below. Use Cost Database sheet for reference pricing.
A6: Unit | B6: Type | C6: Kitchen | D6: Bathroom | E6: Flooring | F6: Paint | G6: Fixtures | H6: Total | I6: Phase | J6: Start Date | K6: Status
A7: 1 | B7: 1BR | C7: 8000 | D7: 6500 | E7: 4500 | F7: 1500 | G7: 2500 | H7: =SUM(C7:G7) | I7: =ROUNDUP(A7/Inputs!$B$20,0) | J7: =DATE(2025,1,1)+((I7-1)*30) | K7: Planned
A8: 2 | B8: 1BR | C8: 8000 | D8: 6500 | E8: 4500 | F8: 1500 | G8: 2500 | H8: =SUM(C8:G8) | I8: =ROUNDUP(A8/Inputs!$B$20,0) | J8: =DATE(2025,1,1)+((I8-1)*30) | K8: Planned
A9: 3 | B9: 2BR | C9: 10000 | D9: 13000 | E9: 6000 | F9: 2000 | G9: 2500 | H9: =SUM(C9:G9) | I9: =ROUNDUP(A9/Inputs!$B$20,0) | J9: =DATE(2025,1,1)+((I9-1)*30) | K9: Planned
A10: 4 | B10: 2BR | C10: 10000 | D10: 13000 | E10: 6000 | F10: 2000 | G10: 2500 | H10: =SUM(C10:G10) | I10: =ROUNDUP(A10/Inputs!$B$20,0) | J10: =DATE(2025,1,1)+((I10-1)*30) | K10: Planned
A11: 5 | B11: 2BR | C11: 10000 | D11: 13000 | E11: 6000 | F11: 2000 | G11: 2500 | H11: =SUM(C11:G11) | I11: =ROUNDUP(A11/Inputs!$B$20,0) | J11: =DATE(2025,1,1)+((I11-1)*30) | K11: Planned
A12: 6 | B12: 3BR | C12: 12000 | D12: 19500 | E12: 7500 | F12: 2500 | G12: 2500 | H12: =SUM(C12:G12) | I12: =ROUNDUP(A12/Inputs!$B$20,0) | J12: =DATE(2025,1,1)+((I12-1)*30) | K12: Planned
A13: 7 | B13: 1BR | C13: 8000 | D13: 6500 | E13: 4500 | F13: 1500 | G13: 2500 | H13: =SUM(C13:G13) | I13: =ROUNDUP(A13/Inputs!$B$20,0) | J13: =DATE(2025,1,1)+((I13-1)*30) | K13: Planned
A14: 8 | B14: 1BR | C14: 8000 | D14: 6500 | E14: 4500 | F14: 1500 | G14: 2500 | H14: =SUM(C14:G14) | I14: =ROUNDUP(A14/Inputs!$B$20,0) | J14: =DATE(2025,1,1)+((I14-1)*30) | K14: Planned
A15: 9 | B15: 2BR | C15: 10000 | D15: 13000 | E15: 6000 | F15: 2000 | G15: 2500 | H15: =SUM(C15:G15) | I15: =ROUNDUP(A15/Inputs!$B$20,0) | J15: =DATE(2025,1,1)+((I15-1)*30) | K15: Planned
A16: 10 | B16: 2BR | C16: 10000 | D16: 13000 | E16: 6000 | F16: 2000 | G16: 2500 | H16: =SUM(C16:G16) | I16: =ROUNDUP(A16/Inputs!$B$20,0) | J16: =DATE(2025,1,1)+((I16-1)*30) | K16: Planned
A17: 11 | B17: 2BR | C17: 10000 | D17: 13000 | E17: 6000 | F17: 2000 | G17: 2500 | H17: =SUM(C17:G17) | I17: =ROUNDUP(A17/Inputs!$B$20,0) | J17: =DATE(2025,1,1)+((I17-1)*30) | K17: Planned
A18: 12 | B18: 3BR | C18: 12000 | D18: 19500 | E18: 7500 | F18: 2500 | G18: 2500 | H18: =SUM(C18:G18) | I18: =ROUNDUP(A18/Inputs!$B$20,0) | J18: =DATE(2025,1,1)+((I18-1)*30) | K18: Planned
... A56: 50 | B56: 1BR | C56: 8000 | D56: 6500 | E56: 4500 | F56: 1500 | G56: 2500 | H56: =SUM(C56:G56) | I56: =ROUNDUP(A56/Inputs!$B$20,0) | J56: =DATE(2025,1,1)+((I56-1)*30) | K56: Planned
A58: CATEGORY TOTALS
A59: Kitchen Renovations | C59: =SUM(C7:C56) | D59: =C10/C100 | E59: =C10/Inputs!$B$4
A60: Bathroom Renovations | C60: =SUM(D7:D56) | D60: =C20/C100 | E60: =C20/Inputs!$B$4
A61: Flooring | C61: =SUM(E7:E56) | D61: =C30/C100 | E61: =C30/Inputs!$B$4
A62: Paint & Finishes | C62: =SUM(F7:F56) | D62: =C40/C100 | E62: =C40/Inputs!$B$4
A63: Appliances & Fixtures | C63: =SUM(G7:G56) | D63: =C50/C100 | E63: =C50/Inputs!$B$4
A64: Exterior Improvements | B64: Enter lump sum amount | C64: 50000 | D64: =C60/C100 | E64: =C60/Inputs!$B$4
A65: Common Areas | B65: Enter lump sum amount | C65: 75000 | D65: =C70/C100 | E65: =C70/Inputs!$B$4
A67: TOTAL RENOVATION BUDGET
A68: Base Renovation Cost: | C68: =C59+C60+C61+C62+C63+C64+C65
A69: Cost per Unit: | C69: =C68/Inputs!$B$4
A70: Cost per SF: | C70: =C68/(Inputs!$B$4*Inputs!$B$6)
A71: Contingency Reserve (10%): | C71: =C68*0.10
A72: ALL-IN BUDGET: | C72: =C68*1.10

Sheet Renovation Phasing
A1: PHASED RENOVATION SCHEDULE
A2: Stagger renovation work to maintain occupancy and cash flow
A4: PROJECT OVERVIEW
A5: Total Units to Renovate: | B5: =Inputs!B4
A6: Units per Phase: | B6: =Inputs!B20
A7: Number of Phases: | B7: =ROUNDUP(B5/B6,0)
A8: Days per Unit: | B8: =Inputs!B21
A9: Total Project Duration (months): | B9: =Inputs!B19
A11: PHASE BREAKDOWN
A12: Phase | B12: Start Date | C12: End Date | D12: Units | E12: Cost | F12: Lost Rent | G12: Holding Costs | H12: Total Cash Out
A13: 1 | B13: =DATE(2025,1,1)+((A13-1)*30) | C13: =B13+Inputs!$B$20*Inputs!$B$21 | D13: =Inputs!$B$20 | E13: =SUMIF('Unit-Level Budget'!$I$7:$I$56,A13,'Unit-Level Budget'!$H$7:$H$56) | F13: =(Inputs!$B$10*Inputs!$B$22/30)*Inputs!$B$20 | G13: =(=(C13-B13)/30)*(Inputs!$B$24+Inputs!$B$25+Inputs!$B$26) | H13: =E13+F13+G13
A14: 2 | B14: =DATE(2025,1,1)+((A14-1)*30) | C14: =B14+Inputs!$B$20*Inputs!$B$21 | D14: =Inputs!$B$20 | E14: =SUMIF('Unit-Level Budget'!$I$7:$I$56,A14,'Unit-Level Budget'!$H$7:$H$56) | F14: =(Inputs!$B$10*Inputs!$B$22/30)*Inputs!$B$20 | G14: =(=(C14-B14)/30)*(Inputs!$B$24+Inputs!$B$25+Inputs!$B$26) | H14: =E14+F14+G14
A15: 3 | B15: =DATE(2025,1,1)+((A15-1)*30) | C15: =B15+Inputs!$B$20*Inputs!$B$21 | D15: =Inputs!$B$20 | E15: =SUMIF('Unit-Level Budget'!$I$7:$I$56,A15,'Unit-Level Budget'!$H$7:$H$56) | F15: =(Inputs!$B$10*Inputs!$B$22/30)*Inputs!$B$20 | G15: =(=(C15-B15)/30)*(Inputs!$B$24+Inputs!$B$25+Inputs!$B$26) | H15: =E15+F15+G15
A16: 4 | B16: =DATE(2025,1,1)+((A16-1)*30) | C16: =B16+Inputs!$B$20*Inputs!$B$21 | D16: =Inputs!$B$20 | E16: =SUMIF('Unit-Level Budget'!$I$7:$I$56,A16,'Unit-Level Budget'!$H$7:$H$56) | F16: =(Inputs!$B$10*Inputs!$B$22/30)*Inputs!$B$20 | G16: =(=(C16-B16)/30)*(Inputs!$B$24+Inputs!$B$25+Inputs!$B$26) | H16: =E16+F16+G16
A17: 5 | B17: =DATE(2025,1,1)+((A17-1)*30) | C17: =B17+Inputs!$B$20*Inputs!$B$21 | D17: =Inputs!$B$20 | E17: =SUMIF('Unit-Level Budget'!$I$7:$I$56,A17,'Unit-Level Budget'!$H$7:$H$56) | F17: =(Inputs!$B$10*Inputs!$B$22/30)*Inputs!$B$20 | G17: =(=(C17-B17)/30)*(Inputs!$B$24+Inputs!$B$25+Inputs!$B$26) | H17: =E17+F17+G17
A18: TOTALS | D18: =SUM(D13:D17) | E18: =SUM(E13:E17) | F18: =SUM(F13:F17) | G18: =SUM(G13:G17) | H18: =SUM(H13:H17)
A21: CASH FLOW IMPACT ANALYSIS
A22: Total Renovation Cost: | B22: ='Unit-Level Budget'!C68
A23: Total Lost Rent: | B23: =F15
A24: Total Holding Costs: | B24: =G15
A25: TOTAL CAPITAL REQUIRED: | B25: =B22+B23+B24
A27: Annual Rent Increase (stabilized): | B27: =(Inputs!B11-Inputs!B10)*12*Inputs!B4
A28: Annual NOI Increase: | B28: =B{row+5}*Inputs!B16
A29: Property Value Creation: | B29: =B{row+6}/Inputs!B15
A31: Net Value Created: | B31: =B{row+7}-B{row+3}
A32: ROI on Total Investment: | B32: =B{row+9}/B{row+3}
A33: Cash-on-Cash Return (Year 1): | B33: =B{row+6}/B{row+3}
