Workbook

Sheet Dashboard
A1: PROPERTY MANAGEMENT DASHBOARD
A2: As of: November 05, 2025
A4: PORTFOLIO SUMMARY
A6: Total Properties | B6: =COUNTA('Property Master'!B4:B1000) -> 1
A7: Total Units | B7: =SUM('Property Master'!H4:H1000) -> 24
A8: Occupied Units | B8: =SUM('Unit Inventory'!L4:L1000) -> 22
A9: Physical Occupancy Rate | B9: =IF(D6>0,D7/D6,0) -> 0
A10: Portfolio Value | B10: =SUM('Property Master'!I4:I1000) -> 3000000
A11: Total Equity Invested | B11: =SUM('ROI Analysis'!E4:E1000) -> 600000
A13: FINANCIAL PERFORMANCE (Monthly)
A15: Gross Potential Rent | B15: =SUM('Rent Roll'!J4:J1000) -> 105600
A16: Vacancy Loss | B16: =SUM('Income Statement'!D4:D1000) -> 5000
A17: Effective Gross Income | B17: =B14+B15 -> 105600
A18: Total Operating Expenses | B18: =SUM('Income Statement'!H4:H1000) -> 15000
A19: Net Operating Income | B19: =B16+B17 -> 110600
A20: Portfolio Cap Rate | B20: =IF(B10>0,(B18*12)/B10,0) -> 0.06
A22: KEY ALERTS
A24: Leases Expiring in 60 Days | B24: =COUNTIFS('Lease Schedule'!E4:E1000,"<="&(TODAY()+60),'Lease Schedule'!E4:E1000,">="&TODAY()) -> 22
A25: Vacant Units | B25: =COUNTIF('Unit Inventory'!E4:E1000,"Vacant") -> 2
A26: Open Maintenance Requests | B26: =COUNTIF('Maintenance Tracker'!G4:G1000,"Open") -> 2
A27: Properties Below Target Occupancy | B27: =COUNTIF('ROI Analysis'!G4:G1000,"<0.9") -> 0

Sheet Property Master
A3: Property ID | B3: Property Name | C3: Address | D3: City | E3: State | F3: Type | G3: Ownership Model | H3: Total Units | I3: Purchase Price | J3: Purchase Date | K3: Current Value | L3: Status | M3: Notes
A4: PROP-001 | B4: Maple Apartments | C4: 123 Main St | D4: New York | E4: NY | F4: Multifamily | G4: Full Ownership | H4: 24 | I4: 3000000 | J4: 44941 | K4: 3200000 | L4: Active

Sheet Ownership Models
A3: Property ID | B3: Property Name | C3: Ownership Type | D3: Details | E3: Master Lease Amount | F3: Lease Start | G3: Lease End | H3: Landlord Approval | I3: Special Terms | J3: Profit Split %
A4: PROP-001 | B4: ='Property Master'!B4 -> Maple Apartments | C4: Full Ownership | D4: 100% Equity Owned

Sheet Unit Inventory
A3: Property ID | B3: Property Name | C3: Unit Number | D3: Unit Type | E3: Status | F3: Beds | G3: Baths | H3: Sq Ft | I3: Market Rent | J3: Current Rent | K3: Tenant Name | L3: Occupied | M3: Days Vacant | N3: Renovation Budget | O3: Notes
A4: PROP-001 | B4: ='Property Master'!B4 -> Maple Apartments | C4: 1A | D4: 1BR/1BA | E4: Occupied | F4: 1 | G4: 1 | H4: 650 | I4: 2500 | J4: 2400 | L4: =IF(E4="Occupied",1,0) -> 1 | M4: =IF(E4="Vacant",30,0) -> 0
A5: PROP-001 | B5: ='Property Master'!B4 -> Maple Apartments | C5: 2A | D5: 1BR/1BA | E5: Occupied | F5: 1 | G5: 1 | H5: 650 | I5: 2500 | J5: 2400 | L5: =IF(E5="Occupied",1,0) -> 1 | M5: =IF(E5="Vacant",30,0) -> 0
A6: PROP-001 | B6: ='Property Master'!B4 -> Maple Apartments | C6: 3A | D6: 1BR/1BA | E6: Occupied | F6: 1 | G6: 1 | H6: 650 | I6: 2500 | J6: 2400 | L6: =IF(E6="Occupied",1,0) -> 1 | M6: =IF(E6="Vacant",30,0) -> 0
A7: PROP-001 | B7: ='Property Master'!B4 -> Maple Apartments | C7: 4A | D7: 1BR/1BA | E7: Occupied | F7: 1 | G7: 1 | H7: 650 | I7: 2500 | J7: 2400 | L7: =IF(E7="Occupied",1,0) -> 1 | M7: =IF(E7="Vacant",30,0) -> 0
A8: PROP-001 | B8: ='Property Master'!B4 -> Maple Apartments | C8: 5A | D8: 1BR/1BA | E8: Occupied | F8: 1 | G8: 1 | H8: 650 | I8: 2500 | J8: 2400 | L8: =IF(E8="Occupied",1,0) -> 1 | M8: =IF(E8="Vacant",30,0) -> 0
A9: PROP-001 | B9: ='Property Master'!B4 -> Maple Apartments | C9: 6A | D9: 1BR/1BA | E9: Occupied | F9: 1 | G9: 1 | H9: 650 | I9: 2500 | J9: 2400 | L9: =IF(E9="Occupied",1,0) -> 1 | M9: =IF(E9="Vacant",30,0) -> 0
A10: PROP-001 | B10: ='Property Master'!B4 -> Maple Apartments | C10: 7A | D10: 1BR/1BA | E10: Occupied | F10: 1 | G10: 1 | H10: 650 | I10: 2500 | J10: 2400 | L10: =IF(E10="Occupied",1,0) -> 1 | M10: =IF(E10="Vacant",30,0) -> 0
A11: PROP-001 | B11: ='Property Master'!B4 -> Maple Apartments | C11: 8A | D11: 1BR/1BA | E11: Occupied | F11: 1 | G11: 1 | H11: 650 | I11: 2500 | J11: 2400 | L11: =IF(E11="Occupied",1,0) -> 1 | M11: =IF(E11="Vacant",30,0) -> 0
A12: PROP-001 | B12: ='Property Master'!B4 -> Maple Apartments | C12: 9A | D12: 1BR/1BA | E12: Occupied | F12: 1 | G12: 1 | H12: 650 | I12: 2500 | J12: 2400 | L12: =IF(E12="Occupied",1,0) -> 1 | M12: =IF(E12="Vacant",30,0) -> 0
A13: PROP-001 | B13: ='Property Master'!B4 -> Maple Apartments | C13: 10A | D13: 1BR/1BA | E13: Occupied | F13: 1 | G13: 1 | H13: 650 | I13: 2500 | J13: 2400 | L13: =IF(E13="Occupied",1,0) -> 1 | M13: =IF(E13="Vacant",30,0) -> 0
A14: PROP-001 | B14: ='Property Master'!B4 -> Maple Apartments | C14: 11A | D14: 1BR/1BA | E14: Occupied | F14: 1 | G14: 1 | H14: 650 | I14: 2500 | J14: 2400 | L14: =IF(E14="Occupied",1,0) -> 1 | M14: =IF(E14="Vacant",30,0) -> 0
A15: PROP-001 | B15: ='Property Master'!B4 -> Maple Apartments | C15: 12A | D15: 1BR/1BA | E15: Occupied | F15: 1 | G15: 1 | H15: 650 | I15: 2500 | J15: 2400 | L15: =IF(E15="Occupied",1,0) -> 1 | M15: =IF(E15="Vacant",30,0) -> 0
A16: PROP-001 | B16: ='Property Master'!B4 -> Maple Apartments | C16: 13A | D16: 1BR/1BA | E16: Occupied | F16: 1 | G16: 1 | H16: 650 | I16: 2500 | J16: 2400 | L16: =IF(E16="Occupied",1,0) -> 1 | M16: =IF(E16="Vacant",30,0) -> 0
A17: PROP-001 | B17: ='Property Master'!B4 -> Maple Apartments | C17: 14A | D17: 1BR/1BA | E17: Occupied | F17: 1 | G17: 1 | H17: 650 | I17: 2500 | J17: 2400 | L17: =IF(E17="Occupied",1,0) -> 1 | M17: =IF(E17="Vacant",30,0) -> 0
A18: PROP-001 | B18: ='Property Master'!B4 -> Maple Apartments | C18: 15A | D18: 1BR/1BA | E18: Occupied | F18: 1 | G18: 1 | H18: 650 | I18: 2500 | J18: 2400 | L18: =IF(E18="Occupied",1,0) -> 1 | M18: =IF(E18="Vacant",30,0) -> 0
A19: PROP-001 | B19: ='Property Master'!B4 -> Maple Apartments | C19: 16A | D19: 1BR/1BA | E19: Occupied | F19: 1 | G19: 1 | H19: 650 | I19: 2500 | J19: 2400 | L19: =IF(E19="Occupied",1,0) -> 1 | M19: =IF(E19="Vacant",30,0) -> 0
A20: PROP-001 | B20: ='Property Master'!B4 -> Maple Apartments | C20: 17A | D20: 1BR/1BA | E20: Occupied | F20: 1 | G20: 1 | H20: 650 | I20: 2500 | J20: 2400 | L20: =IF(E20="Occupied",1,0) -> 1 | M20: =IF(E20="Vacant",30,0) -> 0
A21: PROP-001 | B21: ='Property Master'!B4 -> Maple Apartments | C21: 18A | D21: 1BR/1BA | E21: Occupied | F21: 1 | G21: 1 | H21: 650 | I21: 2500 | J21: 2400 | L21: =IF(E21="Occupied",1,0) -> 1 | M21: =IF(E21="Vacant",30,0) -> 0
A22: PROP-001 | B22: ='Property Master'!B4 -> Maple Apartments | C22: 19A | D22: 1BR/1BA | E22: Occupied | F22: 1 | G22: 1 | H22: 650 | I22: 2500 | J22: 2400 | L22: =IF(E22="Occupied",1,0) -> 1 | M22: =IF(E22="Vacant",30,0) -> 0
A23: PROP-001 | B23: ='Property Master'!B4 -> Maple Apartments | C23: 20A | D23: 1BR/1BA | E23: Occupied | F23: 1 | G23: 1 | H23: 650 | I23: 2500 | J23: 2400 | L23: =IF(E23="Occupied",1,0) -> 1 | M23: =IF(E23="Vacant",30,0) -> 0
A24: PROP-001 | B24: ='Property Master'!B4 -> Maple Apartments | C24: 21A | D24: 1BR/1BA | E24: Occupied | F24: 1 | G24: 1 | H24: 650 | I24: 2500 | J24: 2400 | L24: =IF(E24="Occupied",1,0) -> 1 | M24: =IF(E24="Vacant",30,0) -> 0
A25: PROP-001 | B25: ='Property Master'!B4 -> Maple Apartments | C25: 22A | D25: 1BR/1BA | E25: Occupied | F25: 1 | G25: 1 | H25: 650 | I25: 2500 | J25: 2400 | L25: =IF(E25="Occupied",1,0) -> 1 | M25: =IF(E25="Vacant",30,0) -> 0
A26: PROP-001 | B26: ='Property Master'!B4 -> Maple Apartments | C26: 23A | D26: 1BR/1BA | E26: Vacant | F26: 1 | G26: 1 | H26: 650 | I26: 2500 | J26: 0 | L26: =IF(E26="Occupied",1,0) -> 0 | M26: =IF(E26="Vacant",30,0) -> 30
A27: PROP-001 | B27: ='Property Master'!B4 -> Maple Apartments | C27: 24A | D27: 1BR/1BA | E27: Vacant | F27: 1 | G27: 1 | H27: 650 | I27: 2500 | J27: 0 | L27: =IF(E27="Occupied",1,0) -> 0 | M27: =IF(E27="Vacant",30,0) -> 30

Sheet Rent Roll
A3: Property ID | B3: Property Name | C3: Unit | D3: Tenant Name | E3: Lease Start | F3: Lease End | G3: Monthly Rent | H3: Security Deposit | I3: Credit Score | J3: Monthly Rent Total | K3: Annual Rent | L3: Lease Status | M3: Notes
A4: PROP-001 | B4: ='Property Master'!B4 -> Maple Apartments | C4: 1A | D4: Tenant 1 | E4: 45292 | F4: 46022 | G4: 2400 | H4: 2400 | I4: 720 | J4: =G4 -> 2400 | K4: =G4*12 -> 28800 | L4: Active
A5: PROP-001 | B5: ='Property Master'!B4 -> Maple Apartments | C5: 2A | D5: Tenant 2 | E5: 45292 | F5: 46022 | G5: 2400 | H5: 2400 | I5: 720 | J5: =G5 -> 2400 | K5: =G5*12 -> 28800 | L5: Active
A6: PROP-001 | B6: ='Property Master'!B4 -> Maple Apartments | C6: 3A | D6: Tenant 3 | E6: 45292 | F6: 46022 | G6: 2400 | H6: 2400 | I6: 720 | J6: =G6 -> 2400 | K6: =G6*12 -> 28800 | L6: Active
A7: PROP-001 | B7: ='Property Master'!B4 -> Maple Apartments | C7: 4A | D7: Tenant 4 | E7: 45292 | F7: 46022 | G7: 2400 | H7: 2400 | I7: 720 | J7: =G7 -> 2400 | K7: =G7*12 -> 28800 | L7: Active
A8: PROP-001 | B8: ='Property Master'!B4 -> Maple Apartments | C8: 5A | D8: Tenant 5 | E8: 45292 | F8: 46022 | G8: 2400 | H8: 2400 | I8: 720 | J8: =G8 -> 2400 | K8: =G8*12 -> 28800 | L8: Active
A9: PROP-001 | B9: ='Property Master'!B4 -> Maple Apartments | C9: 6A | D9: Tenant 6 | E9: 45292 | F9: 46022 | G9: 2400 | H9: 2400 | I9: 720 | J9: =G9 -> 2400 | K9: =G9*12 -> 28800 | L9: Active
A10: PROP-001 | B10: ='Property Master'!B4 -> Maple Apartments | C10: 7A | D10: Tenant 7 | E10: 45292 | F10: 46022 | G10: 2400 | H10: 2400 | I10: 720 | J10: =G10 -> 2400 | K10: =G10*12 -> 28800 | L10: Active
A11: PROP-001 | B11: ='Property Master'!B4 -> Maple Apartments | C11: 8A | D11: Tenant 8 | E11: 45292 | F11: 46022 | G11: 2400 | H11: 2400 | I11: 720 | J11: =G11 -> 2400 | K11: =G11*12 -> 28800 | L11: Active
A12: PROP-001 | B12: ='Property Master'!B4 -> Maple Apartments | C12: 9A | D12: Tenant 9 | E12: 45292 | F12: 46022 | G12: 2400 | H12: 2400 | I12: 720 | J12: =G12 -> 2400 | K12: =G12*12 -> 28800 | L12: Active
A13: PROP-001 | B13: ='Property Master'!B4 -> Maple Apartments | C13: 10A | D13: Tenant 10 | E13: 45292 | F13: 46022 | G13: 2400 | H13: 2400 | I13: 720 | J13: =G13 -> 2400 | K13: =G13*12 -> 28800 | L13: Active
A14: PROP-001 | B14: ='Property Master'!B4 -> Maple Apartments | C14: 11A | D14: Tenant 11 | E14: 45292 | F14: 46022 | G14: 2400 | H14: 2400 | I14: 720 | J14: =G14 -> 2400 | K14: =G14*12 -> 28800 | L14: Active
A15: PROP-001 | B15: ='Property Master'!B4 -> Maple Apartments | C15: 12A | D15: Tenant 12 | E15: 45292 | F15: 46022 | G15: 2400 | H15: 2400 | I15: 720 | J15: =G15 -> 2400 | K15: =G15*12 -> 28800 | L15: Active
A16: PROP-001 | B16: ='Property Master'!B4 -> Maple Apartments | C16: 13A | D16: Tenant 13 | E16: 45292 | F16: 46022 | G16: 2400 | H16: 2400 | I16: 720 | J16: =G16 -> 2400 | K16: =G16*12 -> 28800 | L16: Active
A17: PROP-001 | B17: ='Property Master'!B4 -> Maple Apartments | C17: 14A | D17: Tenant 14 | E17: 45292 | F17: 46022 | G17: 2400 | H17: 2400 | I17: 720 | J17: =G17 -> 2400 | K17: =G17*12 -> 28800 | L17: Active
A18: PROP-001 | B18: ='Property Master'!B4 -> Maple Apartments | C18: 15A | D18: Tenant 15 | E18: 45292 | F18: 46022 | G18: 2400 | H18: 2400 | I18: 720 | J18: =G18 -> 2400 | K18: =G18*12 -> 28800 | L18: Active
A19: PROP-001 | B19: ='Property Master'!B4 -> Maple Apartments | C19: 16A | D19: Tenant 16 | E19: 45292 | F19: 46022 | G19: 2400 | H19: 2400 | I19: 720 | J19: =G19 -> 2400 | K19: =G19*12 -> 28800 | L19: Active
A20: PROP-001 | B20: ='Property Master'!B4 -> Maple Apartments | C20: 17A | D20: Tenant 17 | E20: 45292 | F20: 46022 | G20: 2400 | H20: 2400 | I20: 720 | J20: =G20 -> 2400 | K20: =G20*12 -> 28800 | L20: Active
A21: PROP-001 | B21: ='Property Master'!B4 -> Maple Apartments | C21: 18A | D21: Tenant 18 | E21: 45292 | F21: 46022 | G21: 2400 | H21: 2400 | I21: 720 | J21: =G21 -> 2400 | K21: =G21*12 -> 28800 | L21: Active
A22: PROP-001 | B22: ='Property Master'!B4 -> Maple Apartments | C22: 19A | D22: Tenant 19 | E22: 45292 | F22: 46022 | G22: 2400 | H22: 2400 | I22: 720 | J22: =G22 -> 2400 | K22: =G22*12 -> 28800 | L22: Active
A23: PROP-001 | B23: ='Property Master'!B4 -> Maple Apartments | C23: 20A | D23: Tenant 20 | E23: 45292 | F23: 46022 | G23: 2400 | H23: 2400 | I23: 720 | J23: =G23 -> 2400 | K23: =G23*12 -> 28800 | L23: Active
A24: PROP-001 | B24: ='Property Master'!B4 -> Maple Apartments | C24: 21A | D24: Tenant 21 | E24: 45292 | F24: 46022 | G24: 2400 | H24: 2400 | I24: 720 | J24: =G24 -> 2400 | K24: =G24*12 -> 28800 | L24: Active
A25: PROP-001 | B25: ='Property Master'!B4 -> Maple Apartments | C25: 22A | D25: Tenant 22 | E25: 45292 | F25: 46022 | G25: 2400 | H25: 2400 | I25: 720 | J25: =G25 -> 2400 | K25: =G25*12 -> 28800 | L25: Active
A27: TOTALS | J27: =SUM(J4:J26) -> 52800 | K27: =SUM(K4:K26) -> 633600

Sheet Income Statement
A3: Property ID | B3: Property Name | C3: Gross Potential Rent | D3: Vacancy Loss | E3: Other Income | F3: Effective Gross Income | G3: Operating Expenses | H3: Total OpEx | I3: Net Operating Income | J3: Debt Service | K3: Cash Flow Before Tax
A4: PROP-001 | B4: ='Property Master'!B4 -> Maple Apartments | C4: =SUMIF('Rent Roll'!A:A,A4,'Rent Roll'!J:J) -> 52800 | D4: =SUMIFS('Unit Inventory'!I:I,'Unit Inventory'!A:A,A4,'Unit Inventory'!E:E,"Vacant") -> 5000 | E4: 500 | F4: =C4+D4+E4 -> 58300 | G4: 15000 | H4: =G4 -> 15000 | I4: =F4-H4 -> 43300 | J4: 8000 | K4: =I4-J4 -> 35300

Sheet Cash Flow
A3: Property ID | B3: Property Name | C3: Jan | D3: Feb | E3: Mar | F3: Apr | G3: May | H3: Jun | I3: Jul | J3: Aug | K3: Sep | L3: Oct | M3: Nov | N3: Dec | O3: Annual Total
A4: Rent Collection
A5: PROP-001 | B5: ='Property Master'!B4 -> Maple Apartments | C5: 52800 | D5: 52800 | E5: 52800 | F5: 52800 | G5: 52800 | H5: 52800 | I5: 52800 | J5: 52800 | K5: 52800 | L5: 52800 | M5: 52800 | N5: 52800 | O5: =SUM(C5:N5) -> 633600

Sheet Lease Schedule
A3: Property ID | B3: Property Name | C3: Unit | D3: Tenant | E3: Lease End | F3: Days Until Expiration | G3: Monthly Rent | H3: Annual Rent | I3: Renewal Probability | J3: Risk Level | K3: Action Required
A4: ='Rent Roll'!A4 -> PROP-001 | B4: ='Rent Roll'!B4 -> Maple Apartments | C4: ='Rent Roll'!C4 -> 1A | D4: ='Rent Roll'!D4 -> Tenant 1 | E4: ='Rent Roll'!F4 -> 46022 | F4: =E4-TODAY() -> 56 | G4: ='Rent Roll'!G4 -> 2400 | H4: ='Rent Roll'!K4 -> 28800 | I4: 0.7 | J4: =IF(F4<60,"CRITICAL",IF(F4<120,"HIGH",IF(F4<180,"MODERATE","LOW"))) -> CRITICAL | K4: =IF(F4<60,"Contact Tenant",IF(F4<120,"Start Renewal Process","Monitor")) -> Contact Tenant
A5: ='Rent Roll'!A5 -> PROP-001 | B5: ='Rent Roll'!B5 -> Maple Apartments | C5: ='Rent Roll'!C5 -> 2A | D5: ='Rent Roll'!D5 -> Tenant 2 | E5: ='Rent Roll'!F5 -> 46022 | F5: =E5-TODAY() -> 56 | G5: ='Rent Roll'!G5 -> 2400 | H5: ='Rent Roll'!K5 -> 28800 | I5: 0.7 | J5: =IF(F5<60,"CRITICAL",IF(F5<120,"HIGH",IF(F5<180,"MODERATE","LOW"))) -> CRITICAL | K5: =IF(F5<60,"Contact Tenant",IF(F5<120,"Start Renewal Process","Monitor")) -> Contact Tenant
A6: ='Rent Roll'!A6 -> PROP-001 | B6: ='Rent Roll'!B6 -> Maple Apartments | C6: ='Rent Roll'!C6 -> 3A | D6: ='Rent Roll'!D6 -> Tenant 3 | E6: ='Rent Roll'!F6 -> 46022 | F6: =E6-TODAY() -> 56 | G6: ='Rent Roll'!G6 -> 2400 | H6: ='Rent Roll'!K6 -> 28800 | I6: 0.7 | J6: =IF(F6<60,"CRITICAL",IF(F6<120,"HIGH",IF(F6<180,"MODERATE","LOW"))) -> CRITICAL | K6: =IF(F6<60,"Contact Tenant",IF(F6<120,"Start Renewal Process","Monitor")) -> Contact Tenant
A7: ='Rent Roll'!A7 -> PROP-001 | B7: ='Rent Roll'!B7 -> Maple Apartments | C7: ='Rent Roll'!C7 -> 4A | D7: ='Rent Roll'!D7 -> Tenant 4 | E7: ='Rent Roll'!F7 -> 46022 | F7: =E7-TODAY() -> 56 | G7: ='Rent Roll'!G7 -> 2400 | H7: ='Rent Roll'!K7 -> 28800 | I7: 0.7 | J7: =IF(F7<60,"CRITICAL",IF(F7<120,"HIGH",IF(F7<180,"MODERATE","LOW"))) -> CRITICAL | K7: =IF(F7<60,"Contact Tenant",IF(F7<120,"Start Renewal Process","Monitor")) -> Contact Tenant
A8: ='Rent Roll'!A8 -> PROP-001 | B8: ='Rent Roll'!B8 -> Maple Apartments | C8: ='Rent Roll'!C8 -> 5A | D8: ='Rent Roll'!D8 -> Tenant 5 | E8: ='Rent Roll'!F8 -> 46022 | F8: =E8-TODAY() -> 56 | G8: ='Rent Roll'!G8 -> 2400 | H8: ='Rent Roll'!K8 -> 28800 | I8: 0.7 | J8: =IF(F8<60,"CRITICAL",IF(F8<120,"HIGH",IF(F8<180,"MODERATE","LOW"))) -> CRITICAL | K8: =IF(F8<60,"Contact Tenant",IF(F8<120,"Start Renewal Process","Monitor")) -> Contact Tenant
A9: ='Rent Roll'!A9 -> PROP-001 | B9: ='Rent Roll'!B9 -> Maple Apartments | C9: ='Rent Roll'!C9 -> 6A | D9: ='Rent Roll'!D9 -> Tenant 6 | E9: ='Rent Roll'!F9 -> 46022 | F9: =E9-TODAY() -> 56 | G9: ='Rent Roll'!G9 -> 2400 | H9: ='Rent Roll'!K9 -> 28800 | I9: 0.7 | J9: =IF(F9<60,"CRITICAL",IF(F9<120,"HIGH",IF(F9<180,"MODERATE","LOW"))) -> CRITICAL | K9: =IF(F9<60,"Contact Tenant",IF(F9<120,"Start Renewal Process","Monitor")) -> Contact Tenant
A10: ='Rent Roll'!A10 -> PROP-001 | B10: ='Rent Roll'!B10 -> Maple Apartments | C10: ='Rent Roll'!C10 -> 7A | D10: ='Rent Roll'!D10 -> Tenant 7 | E10: ='Rent Roll'!F10 -> 46022 | F10: =E10-TODAY() -> 56 | G10: ='Rent Roll'!G10 -> 2400 | H10: ='Rent Roll'!K10 -> 28800 | I10: 0.7 | J10: =IF(F10<60,"CRITICAL",IF(F10<120,"HIGH",IF(F10<180,"MODERATE","LOW"))) -> CRITICAL | K10: =IF(F10<60,"Contact Tenant",IF(F10<120,"Start Renewal Process","Monitor")) -> Contact Tenant
A11: ='Rent Roll'!A11 -> PROP-001 | B11: ='Rent Roll'!B11 -> Maple Apartments | C11: ='Rent Roll'!C11 -> 8A | D11: ='Rent Roll'!D11 -> Tenant 8 | E11: ='Rent Roll'!F11 -> 46022 | F11: =E11-TODAY() -> 56 | G11: ='Rent Roll'!G11 -> 2400 | H11: ='Rent Roll'!K11 -> 28800 | I11: 0.7 | J11: =IF(F11<60,"CRITICAL",IF(F11<120,"HIGH",IF(F11<180,"MODERATE","LOW"))) -> CRITICAL | K11: =IF(F11<60,"Contact Tenant",IF(F11<120,"Start Renewal Process","Monitor")) -> Contact Tenant
A12: ='Rent Roll'!A12 -> PROP-001 | B12: ='Rent Roll'!B12 -> Maple Apartments | C12: ='Rent Roll'!C12 -> 9A | D12: ='Rent Roll'!D12 -> Tenant 9 | E12: ='Rent Roll'!F12 -> 46022 | F12: =E12-TODAY() -> 56 | G12: ='Rent Roll'!G12 -> 2400 | H12: ='Rent Roll'!K12 -> 28800 | I12: 0.7 | J12: =IF(F12<60,"CRITICAL",IF(F12<120,"HIGH",IF(F12<180,"MODERATE","LOW"))) -> CRITICAL | K12: =IF(F12<60,"Contact Tenant",IF(F12<120,"Start Renewal Process","Monitor")) -> Contact Tenant
A13: ='Rent Roll'!A13 -> PROP-001 | B13: ='Rent Roll'!B13 -> Maple Apartments | C13: ='Rent Roll'!C13 -> 10A | D13: ='Rent Roll'!D13 -> Tenant 10 | E13: ='Rent Roll'!F13 -> 46022 | F13: =E13-TODAY() -> 56 | G13: ='Rent Roll'!G13 -> 2400 | H13: ='Rent Roll'!K13 -> 28800 | I13: 0.7 | J13: =IF(F13<60,"CRITICAL",IF(F13<120,"HIGH",IF(F13<180,"MODERATE","LOW"))) -> CRITICAL | K13: =IF(F13<60,"Contact Tenant",IF(F13<120,"Start Renewal Process","Monitor")) -> Contact Tenant
A14: ='Rent Roll'!A14 -> PROP-001 | B14: ='Rent Roll'!B14 -> Maple Apartments | C14: ='Rent Roll'!C14 -> 11A | D14: ='Rent Roll'!D14 -> Tenant 11 | E14: ='Rent Roll'!F14 -> 46022 | F14: =E14-TODAY() -> 56 | G14: ='Rent Roll'!G14 -> 2400 | H14: ='Rent Roll'!K14 -> 28800 | I14: 0.7 | J14: =IF(F14<60,"CRITICAL",IF(F14<120,"HIGH",IF(F14<180,"MODERATE","LOW"))) -> CRITICAL | K14: =IF(F14<60,"Contact Tenant",IF(F14<120,"Start Renewal Process","Monitor")) -> Contact Tenant
A15: ='Rent Roll'!A15 -> PROP-001 | B15: ='Rent Roll'!B15 -> Maple Apartments | C15: ='Rent Roll'!C15 -> 12A | D15: ='Rent Roll'!D15 -> Tenant 12 | E15: ='Rent Roll'!F15 -> 46022 | F15: =E15-TODAY() -> 56 | G15: ='Rent Roll'!G15 -> 2400 | H15: ='Rent Roll'!K15 -> 28800 | I15: 0.7 | J15: =IF(F15<60,"CRITICAL",IF(F15<120,"HIGH",IF(F15<180,"MODERATE","LOW"))) -> CRITICAL | K15: =IF(F15<60,"Contact Tenant",IF(F15<120,"Start Renewal Process","Monitor")) -> Contact Tenant
... A25: ='Rent Roll'!A25 -> PROP-001 | B25: ='Rent Roll'!B25 -> Maple Apartments | C25: ='Rent Roll'!C25 -> 22A | D25: ='Rent Roll'!D25 -> Tenant 22 | E25: ='Rent Roll'!F25 -> 46022 | F25: =E25-TODAY() -> 56 | G25: ='Rent Roll'!G25 -> 2400 | H25: ='Rent Roll'!K25 -> 28800 | I25: 0.7 | J25: =IF(F25<60,"CRITICAL",IF(F25<120,"HIGH",IF(F25<180,"MODERATE","LOW"))) -> CRITICAL | K25: =IF(F25<60,"Contact Tenant",IF(F25<120,"Start Renewal Process","Monitor")) -> Contact Tenant

Sheet Maintenance Tracker
A3: Request ID | B3: Property ID | C3: Property Name | D3: Unit | E3: Category | F3: Description | G3: Status | H3: Priority | I3: Date Reported | J3: Date Completed | K3: Cost | L3: Vendor | M3: Notes
A4: MNT-001 | B4: PROP-001 | C4: ='Property Master'!B4 -> Maple Apartments | D4: 1A | E4: Plumbing | F4: Repair needed | G4: Open | H4: Emergency | I4: 45966.866
A5: MNT-002 | B5: PROP-001 | C5: ='Property Master'!B4 -> Maple Apartments | D5: 2A | E5: Electrical | F5: Repair needed | G5: In Progress | H5: High | I5: 45966.866
A6: MNT-003 | B6: PROP-001 | C6: ='Property Master'!B4 -> Maple Apartments | D6: 3A | E6: HVAC | F6: Repair needed | G6: Completed | H6: Medium | I6: 45966.866 | J6: 45966.866 | K6: 350
A7: MNT-004 | B7: PROP-001 | C7: ='Property Master'!B4 -> Maple Apartments | D7: 4A | E7: Appliance | F7: Repair needed | G7: Open | H7: Low | I7: 45966.866
A8: MNT-005 | B8: PROP-001 | C8: ='Property Master'!B4 -> Maple Apartments | D8: 5A | E8: General | F8: Repair needed | G8: In Progress | H8: Emergency | I8: 45966.866
A9: MNT-006 | B9: PROP-001 | C9: ='Property Master'!B4 -> Maple Apartments | D9: 6A | E9: Plumbing | F9: Repair needed | G9: Completed | H9: High | I9: 45966.866 | J9: 45966.866 | K9: 350

Sheet ROI Analysis
A3: Property ID | B3: Property Name | C3: Ownership Model | D3: Purchase Price | E3: Total Equity | F3: Current Value | G3: Annual NOI | H3: Annual Cash Flow | I3: Appreciation | J3: Total Return | K3: Cash-on-Cash Return | L3: ROI | M3: IRR (Approx) | N3: Years Held
A4: PROP-001 | B4: ='Property Master'!B4 -> Maple Apartments | C4: ='Ownership Models'!C4 -> Full Ownership | D4: ='Property Master'!I4 -> 3000000 | E4: 600000 | F4: ='Property Master'!K4 -> 3200000 | G4: =SUMIF('Income Statement'!A:A,A4,'Income Statement'!I:I)*12 -> 519600 | H4: =SUMIF('Income Statement'!A:A,A4,'Income Statement'!K:K)*12 -> 423600 | I4: =F4-D4 -> 200000 | J4: =I4+SUM(H4) -> 623600 | K4: =IF(E4>0,H4/E4,0) -> 0.706 | L4: =IF(E4>0,J4/E4,0) -> 1.0393333 | M4: =IF(E4>0,(POWER((F4+H4)/E4,1/N4)-1),0) -> 0.89717887 | N4: =(TODAY()-'Property Master'!J4)/365 -> 2.8082192

Sheet Budget vs Actual
A3: Property ID | B3: Property Name | C3: Category | D3: Budget (Monthly) | E3: Actual (Monthly) | F3: Variance $ | G3: Variance % | H3: YTD Budget | I3: YTD Actual | J3: YTD Variance | K3: Status
A4: PROP-001 | B4: ='Property Master'!B4 -> Maple Apartments | C4: Property Taxes | D4: 1200 | E4: 1150 | F4: =E4-D4 -> -50 | G4: =IF(D4>0,F4/D4,0) -> -0.041666667 | H4: =D4*12 -> 14400 | I4: =E4*12 -> 13800 | J4: =I4-H4 -> -600 | K4: =IF(ABS(G4)<0.05,"On Track",IF(F4<0,"Under Budget","Over Budget")) -> On Track
A5: PROP-001 | B5: ='Property Master'!B4 -> Maple Apartments | C5: Insurance | D5: 1200 | E5: 1150 | F5: =E5-D5 -> -50 | G5: =IF(D5>0,F5/D5,0) -> -0.041666667 | H5: =D5*12 -> 14400 | I5: =E5*12 -> 13800 | J5: =I5-H5 -> -600 | K5: =IF(ABS(G5)<0.05,"On Track",IF(F5<0,"Under Budget","Over Budget")) -> On Track
A6: PROP-001 | B6: ='Property Master'!B4 -> Maple Apartments | C6: Utilities | D6: 1200 | E6: 1150 | F6: =E6-D6 -> -50 | G6: =IF(D6>0,F6/D6,0) -> -0.041666667 | H6: =D6*12 -> 14400 | I6: =E6*12 -> 13800 | J6: =I6-H6 -> -600 | K6: =IF(ABS(G6)<0.05,"On Track",IF(F6<0,"Under Budget","Over Budget")) -> On Track
A7: PROP-001 | B7: ='Property Master'!B4 -> Maple Apartments | C7: Maintenance | D7: 1200 | E7: 1150 | F7: =E7-D7 -> -50 | G7: =IF(D7>0,F7/D7,0) -> -0.041666667 | H7: =D7*12 -> 14400 | I7: =E7*12 -> 13800 | J7: =I7-H7 -> -600 | K7: =IF(ABS(G7)<0.05,"On Track",IF(F7<0,"Under Budget","Over Budget")) -> On Track
A8: PROP-001 | B8: ='Property Master'!B4 -> Maple Apartments | C8: Management | D8: 1200 | E8: 1150 | F8: =E8-D8 -> -50 | G8: =IF(D8>0,F8/D8,0) -> -0.041666667 | H8: =D8*12 -> 14400 | I8: =E8*12 -> 13800 | J8: =I8-H8 -> -600 | K8: =IF(ABS(G8)<0.05,"On Track",IF(F8<0,"Under Budget","Over Budget")) -> On Track
A9: PROP-001 | B9: ='Property Master'!B4 -> Maple Apartments | C9: Marketing | D9: 1200 | E9: 1150 | F9: =E9-D9 -> -50 | G9: =IF(D9>0,F9/D9,0) -> -0.041666667 | H9: =D9*12 -> 14400 | I9: =E9*12 -> 13800 | J9: =I9-H9 -> -600 | K9: =IF(ABS(G9)<0.05,"On Track",IF(F9<0,"Under Budget","Over Budget")) -> On Track
A10: PROP-001 | B10: ='Property Master'!B4 -> Maple Apartments | C10: Landscaping | D10: 1200 | E10: 1150 | F10: =E10-D10 -> -50 | G10: =IF(D10>0,F10/D10,0) -> -0.041666667 | H10: =D10*12 -> 14400 | I10: =E10*12 -> 13800 | J10: =I10-H10 -> -600 | K10: =IF(ABS(G10)<0.05,"On Track",IF(F10<0,"Under Budget","Over Budget")) -> On Track
A11: PROP-001 | B11: ='Property Master'!B4 -> Maple Apartments | C11: Pest Control | D11: 1200 | E11: 1150 | F11: =E11-D11 -> -50 | G11: =IF(D11>0,F11/D11,0) -> -0.041666667 | H11: =D11*12 -> 14400 | I11: =E11*12 -> 13800 | J11: =I11-H11 -> -600 | K11: =IF(ABS(G11)<0.05,"On Track",IF(F11<0,"Under Budget","Over Budget")) -> On Track

Sheet Settings
A1: PROPERTY MANAGEMENT SYSTEM - SETTINGS
A3: GLOBAL ASSUMPTIONS
A4: Default Vacancy Rate | B4: 0.05 | C4: 5% vacancy for new properties
A5: Target Occupancy Rate | B5: 0.95 | C5: 95% occupancy target
A6: Annual Rent Growth | B6: 0.03 | C6: 3% annual increase
A7: Maintenance Reserve (% of Rent) | B7: 0.05 | C7: 5% of gross rent
A8: Management Fee (%) | B8: 0.08 | C8: 8% of gross income
A9: Default Cap Rate | B9: 0.06 | C9: 6% for valuation
A11: PROPERTY TYPES
A12: Multifamily
A13: Single Family
A14: Commercial Office
A15: Retail
A16: Industrial
A17: Mixed-Use
A18: Hotel/Hospitality
A20: OWNERSHIP MODELS
A21: Full Ownership
A22: Master Lease
A23: Sublease
... A30: COLOR CODING LEGEND
A31: Blue Text | B31: User inputs - Change these values for your properties
A32: Black Text | B32: Formulas - Automatically calculated
A33: Green Text | B33: Links to other sheets - Pull data from elsewhere
A34: Yellow Background | B34: Important assumptions - Review carefully
