Workbook

Sheet Instructions1
B2: DUE DILIGENCE TRACKER - USER GUIDE
B5: OVERVIEW
B6: This Due Diligence Tracker is a comprehensive tool for managing the entire due diligence process for M&A, LBO, or investment transactions.
B7: It integrates with the DCF and LBO valuation models to provide end-to-end deal analysis capabilities.
B9: COLOR CODING SYSTEM
B10: 🔵 Blue text with yellow highlight = INPUT CELLS (your data)
B11: ⚫ Black text = FORMULAS (automatically calculated)
B12: 🟢 Green text = LINKS to other sheets
B14: WORKSHEET GUIDE
B16: 1. EXECUTIVE SUMMARY
B17: • Dashboard with key metrics and progress tracking
B18: • Overall completion percentages
... B90: and LBO Model Guide included in your toolkit.

Sheet Instructions
B2: DUE DILIGENCE TRACKER - USER GUIDE
B4: PURPOSE | C4: This Due Diligence Tracker helps manage comprehensive DD across all workstreams for M&A transactions, LBOs, and strategic investments.
B6: SHEETS OVERVIEW
B7: 1. Executive Summary | C7: High-level dashboard showing overall progress, workstream status, and risk summary
B8: 2. Master Checklist | C8: Comprehensive checklist of 150+ DD items across all categories
B9: 3. Financial DD Detail | C9: Detailed financial due diligence items and findings
B10: 4. Legal DD Detail | C10: Legal and regulatory DD items
B11: 5. Commercial DD Detail | C11: Market, customer, and competitive analysis
B12: 6. Issue Log | C12: Track all due diligence issues and red flags
B13: 7. Risk Register | C13: Comprehensive risk assessment and mitigation
B14: 8. Document Tracker | C14: Track all requested and received documents
B15: 9. Timeline & Milestones | C15: Track key DD milestones and deadlines
B16: 10. Integration w/ Models | C16: Links to DCF and LBO models
B18: COLOR CODING
B19: Blue text with yellow highlight
B20: Black text
B21: Green text
B23: HOW TO USE
B24: Step 1 | C24: Enter deal information in Executive Summary
B25: Step 2 | C25: Update Master Checklist as you receive documents
B26: Step 3 | C26: Log any issues in Issue Log with severity
B27: Step 4 | C27: Track risks in Risk Register
B28: Step 5 | C28: Review Executive Summary dashboard for overall progress
B30: INTEGRATION
C31: This tracker is designed to integrate with your DCF and LBO models.
C32: Key findings flow into valuation assumptions and risk adjustments.
C33: See 'Integration w/ Models' sheet for linking instructions.

Sheet Executive Summary
B2: DUE DILIGENCE TRACKER - EXECUTIVE SUMMARY
B4: DEAL INFORMATION | G4: OVERALL PROGRESS
B5: Target Company: | C5: Enter Company Name | G5: Total Items: | H5: =COUNTA('Master Checklist'!B11:B500) -> 140
B6: Transaction Type: | C6: LBO / Strategic / Minority | G6: Completed: | H6: =COUNTIF('Master Checklist'!J11:J500,"Complete") -> 0
B7: Deal Size ($M): | C7: 0 | G7: In Progress: | H7: =COUNTIF('Master Checklist'!J11:J500,"In Progress") -> 0
B8: DD Start Date: | C8: 45959.445 | G8: Not Started: | H8: =COUNTIF('Master Checklist'!J11:J500,"Not Started") -> 0
B9: Target Close Date: | C9: 46019.445 | G9: % Complete: | H9: =IFERROR(H6/H5,0) -> 0
B10: Days Remaining: | C10: =C9-C8 -> 60
B11: Lead Partner: | C11: Name
B14: WORKSTREAM PROGRESS
B15: Workstream | C15: Total | D15: Complete | E15: In Progress | F15: Not Started | G15: % Done | H15: Status
B16: Financial DD | C16: =COUNTIF('Master Checklist'!$C$11:$C$500,"Financial DD") -> 0 | D16: =COUNTIFS('Master Checklist'!$C$11:$C$500,"Financial DD",'Master Checklist'!$J$11:$J$500,"Complete") -> 0 | E16: =COUNTIFS('Master Checklist'!$C$11:$C$500,"Financial DD",'Master Checklist'!$J$11:$J$500,"In Progress") -> 0 | F16: =COUNTIFS('Master Checklist'!$C$11:$C$500,"Financial DD",'Master Checklist'!$J$11:$J$500,"Not Started") -> 0 | G16: =IFERROR(D16/C16,0) -> 0 | H16: =IF(G16>=0.9,"✓",IF(G16>=0.5,"!","✗")) -> ✗
B17: Legal & Regulatory | C17: =COUNTIF('Master Checklist'!$C$11:$C$500,"Legal & Regulatory") -> 0 | D17: =COUNTIFS('Master Checklist'!$C$11:$C$500,"Legal & Regulatory",'Master Checklist'!$J$11:$J$500,"Complete") -> 0 | E17: =COUNTIFS('Master Checklist'!$C$11:$C$500,"Legal & Regulatory",'Master Checklist'!$J$11:$J$500,"In Progress") -> 0 | F17: =COUNTIFS('Master Checklist'!$C$11:$C$500,"Legal & Regulatory",'Master Checklist'!$J$11:$J$500,"Not Started") -> 0 | G17: =IFERROR(D17/C17,0) -> 0 | H17: =IF(G17>=0.9,"✓",IF(G17>=0.5,"!","✗")) -> ✗
B18: Commercial DD | C18: =COUNTIF('Master Checklist'!$C$11:$C$500,"Commercial DD") -> 0 | D18: =COUNTIFS('Master Checklist'!$C$11:$C$500,"Commercial DD",'Master Checklist'!$J$11:$J$500,"Complete") -> 0 | E18: =COUNTIFS('Master Checklist'!$C$11:$C$500,"Commercial DD",'Master Checklist'!$J$11:$J$500,"In Progress") -> 0 | F18: =COUNTIFS('Master Checklist'!$C$11:$C$500,"Commercial DD",'Master Checklist'!$J$11:$J$500,"Not Started") -> 0 | G18: =IFERROR(D18/C18,0) -> 0 | H18: =IF(G18>=0.9,"✓",IF(G18>=0.5,"!","✗")) -> ✗
B19: Operational DD | C19: =COUNTIF('Master Checklist'!$C$11:$C$500,"Operational DD") -> 0 | D19: =COUNTIFS('Master Checklist'!$C$11:$C$500,"Operational DD",'Master Checklist'!$J$11:$J$500,"Complete") -> 0 | E19: =COUNTIFS('Master Checklist'!$C$11:$C$500,"Operational DD",'Master Checklist'!$J$11:$J$500,"In Progress") -> 0 | F19: =COUNTIFS('Master Checklist'!$C$11:$C$500,"Operational DD",'Master Checklist'!$J$11:$J$500,"Not Started") -> 0 | G19: =IFERROR(D19/C19,0) -> 0 | H19: =IF(G19>=0.9,"✓",IF(G19>=0.5,"!","✗")) -> ✗
B20: IT / Technology | C20: =COUNTIF('Master Checklist'!$C$11:$C$500,"IT / Technology") -> 0 | D20: =COUNTIFS('Master Checklist'!$C$11:$C$500,"IT / Technology",'Master Checklist'!$J$11:$J$500,"Complete") -> 0 | E20: =COUNTIFS('Master Checklist'!$C$11:$C$500,"IT / Technology",'Master Checklist'!$J$11:$J$500,"In Progress") -> 0 | F20: =COUNTIFS('Master Checklist'!$C$11:$C$500,"IT / Technology",'Master Checklist'!$J$11:$J$500,"Not Started") -> 0 | G20: =IFERROR(D20/C20,0) -> 0 | H20: =IF(G20>=0.9,"✓",IF(G20>=0.5,"!","✗")) -> ✗
B21: HR / Organization | C21: =COUNTIF('Master Checklist'!$C$11:$C$500,"HR / Organization") -> 0 | D21: =COUNTIFS('Master Checklist'!$C$11:$C$500,"HR / Organization",'Master Checklist'!$J$11:$J$500,"Complete") -> 0 | E21: =COUNTIFS('Master Checklist'!$C$11:$C$500,"HR / Organization",'Master Checklist'!$J$11:$J$500,"In Progress") -> 0 | F21: =COUNTIFS('Master Checklist'!$C$11:$C$500,"HR / Organization",'Master Checklist'!$J$11:$J$500,"Not Started") -> 0 | G21: =IFERROR(D21/C21,0) -> 0 | H21: =IF(G21>=0.9,"✓",IF(G21>=0.5,"!","✗")) -> ✗
B22: Tax DD | C22: =COUNTIF('Master Checklist'!$C$11:$C$500,"Tax DD") -> 0 | D22: =COUNTIFS('Master Checklist'!$C$11:$C$500,"Tax DD",'Master Checklist'!$J$11:$J$500,"Complete") -> 0 | E22: =COUNTIFS('Master Checklist'!$C$11:$C$500,"Tax DD",'Master Checklist'!$J$11:$J$500,"In Progress") -> 0 | F22: =COUNTIFS('Master Checklist'!$C$11:$C$500,"Tax DD",'Master Checklist'!$J$11:$J$500,"Not Started") -> 0 | G22: =IFERROR(D22/C22,0) -> 0 | H22: =IF(G22>=0.9,"✓",IF(G22>=0.5,"!","✗")) -> ✗
B23: Environmental | C23: =COUNTIF('Master Checklist'!$C$11:$C$500,"Environmental") -> 0 | D23: =COUNTIFS('Master Checklist'!$C$11:$C$500,"Environmental",'Master Checklist'!$J$11:$J$500,"Complete") -> 0 | E23: =COUNTIFS('Master Checklist'!$C$11:$C$500,"Environmental",'Master Checklist'!$J$11:$J$500,"In Progress") -> 0 | F23: =COUNTIFS('Master Checklist'!$C$11:$C$500,"Environmental",'Master Checklist'!$J$11:$J$500,"Not Started") -> 0 | G23: =IFERROR(D23/C23,0) -> 0 | H23: =IF(G23>=0.9,"✓",IF(G23>=0.5,"!","✗")) -> ✗
B26: RISK & ISSUE SUMMARY
B27: Risk Level | C27: Count | D27: Open Issues
B28: High | C28: =COUNTIF('Master Checklist'!C10:C500,"Operational DD") -> 0 | D28: =COUNTIFS('Master Checklist'!C10:C500,"Operational DD",'Master Checklist'!F10:F500,"Complete") -> 0
B29: Medium | C29: =COUNTIF('Master Checklist'!C10:C500,"IT/Technology") -> 0 | D29: =COUNTIFS('Master Checklist'!C10:C500,"IT/Technology",'Master Checklist'!F10:F500,"Complete") -> 0
B30: Low | C30: =COUNTIF('Master Checklist'!C10:C500,"ESG DD") -> 0 | D30: =COUNTIFS('Master Checklist'!C10:C500,"ESG DD",'Master Checklist'!F10:F500,"Complete") -> 0
B33: KEY FINDINGS & RED FLAGS
B34: Critical Issues: | C34: =COUNTIF('Master Checklist'!C10:C500,"HR & People") -> 0
B35: Deal Breakers: | C35: =COUNTIFS('Master Checklist'!C10:C500,"HR & People",'Master Checklist'!F10:F500,"Complete") -> 0 | D35: =COUNTIFS('Master Checklist'!C10:C500,"HR & People",'Master Checklist'!F10:F500,"Complete") -> 0

Sheet Master Checklist
B2: COMPREHENSIVE DUE DILIGENCE MASTER CHECKLIST
B4: Instructions: Track all DD items. Update Status, Responsible Party. Flag issues in Issue Log. Color code: Blue = Input, Black = Formula, Green = Link
B6: # | C6: Category | D6: Workstream | E6: Item Description | F6: Document/Data Required | G6: Priority | H6: Responsible | I6: Due Date | J6: Date Rcvd | K6: Status | L6: % Done | M6: Risk | N6: Notes
B11: 1 | C11: I.A | D11: Financial DD | E11: Historical Financials | F11: 5 years audited P&L, BS, CF | G11: Critical | K11: Not Started | L11: =IF(J11="Complete",1,IF(J11="In Progress",0.5,0)) -> 0
B12: 2 | C12: I.A | D12: Financial DD | E12: Monthly Financials | F12: Latest 12 months unaudited | G12: Critical | K12: Not Started | L12: =IF(J12="Complete",1,IF(J12="In Progress",0.5,0)) -> 0
B13: 3 | C13: I.A | D13: Financial DD | E13: Quality of Earnings | F13: Detailed QoE analysis with add-backs | G13: Critical | K13: Not Started | L13: =IF(J13="Complete",1,IF(J13="In Progress",0.5,0)) -> 0
B14: 4 | C14: I.A | D14: Financial DD | E14: Revenue by Customer | F14: Customer concentration (3 years) | G14: High | K14: Not Started | L14: =IF(J14="Complete",1,IF(J14="In Progress",0.5,0)) -> 0
B15: 5 | C15: I.A | D15: Financial DD | E15: Revenue by Product | F15: Product/service mix analysis | G15: High | K15: Not Started | L15: =IF(J15="Complete",1,IF(J15="In Progress",0.5,0)) -> 0
B16: 6 | C16: I.A | D16: Financial DD | E16: Revenue Recognition | F16: ASC 606 policies and compliance | G16: High | K16: Not Started | L16: =IF(J16="Complete",1,IF(J16="In Progress",0.5,0)) -> 0
B17: 7 | C17: I.A | D17: Financial DD | E17: Recurring Revenue | F17: MRR/ARR breakdown and retention | G17: High | K17: Not Started | L17: =IF(J17="Complete",1,IF(J17="In Progress",0.5,0)) -> 0
B18: 8 | C18: I.A | D18: Financial DD | E18: Backlog Analysis | F18: Contracted not yet recognized | G18: Medium | K18: Not Started | L18: =IF(J18="Complete",1,IF(J18="In Progress",0.5,0)) -> 0
B19: 9 | C19: I.A | D19: Financial DD | E19: Working Capital | F19: A/R, Inventory, A/P analysis | G19: Critical | K19: Not Started | L19: =IF(J19="Complete",1,IF(J19="In Progress",0.5,0)) -> 0
B20: 10 | C20: I.A | D20: Financial DD | E20: A/R Aging | F20: Detailed receivables aging report | G20: High | K20: Not Started | L20: =IF(J20="Complete",1,IF(J20="In Progress",0.5,0)) -> 0
B21: 11 | C21: I.A | D21: Financial DD | E21: Bad Debt Reserve | F21: Historical bad debt experience | G21: Medium | K21: Not Started | L21: =IF(J21="Complete",1,IF(J21="In Progress",0.5,0)) -> 0
B22: 12 | C22: I.A | D22: Financial DD | E22: Inventory Analysis | F22: Raw, WIP, finished goods | G22: High | K22: Not Started | L22: =IF(J22="Complete",1,IF(J22="In Progress",0.5,0)) -> 0
... B150: 140 | C150: IX.C | D150: Environmental | E150: Environmental Liabilities | F150: Known/potential liabilities | G150: Critical | K150: Not Started | L150: =IF(J150="Complete",1,IF(J150="In Progress",0.5,0)) -> 0

Sheet Risk Assessment Copy

Sheet Integration with Models
B2: INTEGRATION WITH DCF AND LBO MODELS
B4: DD FINDINGS IMPACT ON VALUATION
B6: Instructions:
B7: 1. Key DD findings should flow into DCF and LBO model assumptions
B8: 2. Adjust revenue growth, margins, CapEx, NWC based on DD discoveries
B9: 3. Factor in identified risks through scenario analysis
B10: 4. Update WACC or discount rate for risk profile changes
B11: 5. Reflect working capital adjustments in purchase price
B14: KEY DD FINDINGS IMPACT TABLE
B15: Finding Category | C15: DD Finding | D15: Impact on Valuation | E15: Model Adjustment | F15: Value Impact ($M)
B16: Revenue | C16: Customer concentration - top 3 = 60% | D16: Increase revenue risk | E16: Lower revenue growth by 2% | F16: -10
B17: EBITDA | C17: One-time legal costs $2M | D17: Add back to normalized EBITDA | E17: Increase EBITDA by $2M | F17: 20
B18: Working Capital | C18: A/R aging shows DSO at 75 days | D18: Higher NWC requirement | E18: Increase NWC by $5M | F18: -5
B19: CapEx | C19: Deferred maintenance approximately $3M | D19: One-time CapEx needed | E19: Add $3M CapEx in Year 1 | F19: -3
B20: Risk | C20: Patent litigation exposure | D20: Increase discount rate | E20: WACC +0.5% | F20: -15
B43: Total Value Impact from DD: | C43: =SUM(F16:F40) -> -13
B45: LINKS TO MODELS
B46: DCF Model Link: | C46: [Link to DCF_Model_Comprehensive.xlsx]
B47: LBO Model Link: | C47: [Link to LBO_Model_Comprehensive.xlsx]
B49: KEY ASSUMPTIONS TO UPDATE IN MODELS:
B50: • Revenue Growth Rates (based on customer and market DD)
B51: • EBITDA Margins (based on QoE analysis)
B52: • Working Capital assumptions (based on NWC analysis)
B53: • CapEx requirements (maintenance + growth)
B54: • WACC or Discount Rate (based on risk assessment)
B55: • Terminal Growth Rate (based on market outlook)
B56: • Exit Multiple (based on comparable transactions)

Sheet Document Repository
B2: DOCUMENT REPOSITORY LOG
B4: Instructions: Log all documents received during due diligence. Link to data room or file locations.
B8: Doc ID | C8: Workstream | D8: Document Type | E8: Document Name | F8: Date Requested | G8: Date Received | H8: Requested By | I8: Provided By | J8: Location/Link | K8: Notes

Sheet Team Tracker
B2: DUE DILIGENCE TEAM & CONTACTS
B4: Instructions: Maintain list of all team members and external contacts involved in due diligence.
B6: INTERNAL TEAM
B8: Name | C8: Role | D8: Workstream | E8: Email | F8: Phone | G8: Company | H8: Active Tasks | I8: Notes
C10: Deal Lead | D10: Overall
C11: Financial Analyst | D11: Financial DD
C12: Legal Counsel | D12: Legal & Regulatory
B25: EXTERNAL ADVISORS & CONTACTS
B27: Firm/Company | C27: Contact Name | D27: Role | E27: Workstream | F27: Email | G27: Phone | H27: Engagement Date | I27: Notes
